rough2fine/prompt.md
rough2fine/server.py
rough2fine-0.2.1.dist-info/METADATA
rough2fine-0.2.1.dist-info/WHEEL
rough2fine-0.2.1.dist-info/entry_points.txt
rough2fine-0.2.1.dist-info/RECORD
