Metadata-Version: 2.3
Name: rough2fine
Version: 0.2.1
Summary: 通过给定的资料，获得细分场
Author: GZT
Author-email: ave1age@163.com
Requires-Python: >=3.10
Classifier: Programming Language :: Python :: 3
Classifier: Programming Language :: Python :: 3.10
Classifier: Programming Language :: Python :: 3.11
Classifier: Programming Language :: Python :: 3.12
Classifier: Programming Language :: Python :: 3.13
Requires-Dist: mcp (>=1.9.4)
